{
	"h": {
		"wet1": "0",
		"wet2": "1.9",
		"wet3": "0.3",
		"wet4": "4.8",
		"wet5": "10",
		"wet6": "22.2",
		"wet7": "21.4",
		"wet8": "20.8",
		"wet9": "16.4",
		"wet10": "18.1",
		"wet11": "25.65",
		"wet12": "19.8",
		"wet13": "0",
		"wet14": "0",
		"wet15": "0",
		"wet16": "0"
	},
	"n": {
		"wet1": "4.7",
		"wet2": "16.9",
		"wet3": "17.7",
		"wet4": "17.7",
		"wet5": "22.4",
		"wet6": "32.8",
		"wet7": "32.2",
		"wet8": "37.4",
		"wet9": "34.1",
		"wet10": "29.7",
		"wet11": "41.25",
		"wet12": "37.9",
		"wet13": "25.05",
		"wet14": "11.4",
		"wet15": "0",
		"wet16": "0"
	},
	"d": {
		"wet1": "16.2",
		"wet2": "22.7",
		"wet3": "25.9",
		"wet4": "21",
		"wet5": "30",
		"wet6": "32.8",
		"wet7": "35.7",
		"wet8": "39.6",
		"wet9": "41.8",
		"wet10": "31.5",
		"wet11": "45.15",
		"wet12": "44.1",
		"wet13": "37.95",
		"wet14": "25.7",
		"wet15": "13.85",
		"wet16": "9.7"
	}
}
